MO_project/__init__.py
MO_project/__main__.py
MO_project/cli.py
MO_project/core.py
MO_project-0.0.1.dist-info/LICENSE
MO_project-0.0.1.dist-info/METADATA
MO_project-0.0.1.dist-info/WHEEL
MO_project-0.0.1.dist-info/entry_points.txt
MO_project-0.0.1.dist-info/top_level.txt
MO_project-0.0.1.dist-info/RECORD
