Metadata-Version: 2.1
Name: MO_project
Version: 0.0.1
Summary: CLI model validation application against moorings
Author-email: Giurato Michele <giurato.michele@cmcc.it>
License-File: LICENSE
